terminaltelemetry-1.0.0.dist-info/licenses/LICENSE
termtel/__init__.py
termtel/config.py
termtel/icon.ico
termtel/logo.py
termtel/logo.svg
termtel/nbtosession.py
termtel/templates.db
termtel/termtel.py
termtel/theme_editor2.py
termtel/theme_launcher.py
termtel/themes2.py
termtel/themes3.py
termtel/config/platforms/platforms.json
termtel/helpers/__init__.py
termtel/helpers/auth_helper.py
termtel/helpers/credslib.py
termtel/helpers/resource_manager.py
termtel/helpers/settings.py
termtel/helpers/theme_bootstrap.py
termtel/helpers/utils.py
termtel/routers/__init__.py
termtel/routers/auth.py
termtel/routers/search.py
termtel/routers/workspace.py
termtel/schemas/__init__.py
termtel/ssh/__init__.py
termtel/ssh/connection_checker.py
termtel/ssh/pysshpass.py
termtel/ssh/ssh_key_config.py
termtel/ssh/ssh_manager.py
termtel/ssh/sshschemahandler.py
termtel/ssh/sshshell.py
termtel/ssh/sshshellreader.py
termtel/static/doom.html
termtel/static/doom.wasm
termtel/static/doom.wasm.sav
termtel/static/main.js
termtel/static/python.webp
termtel/static/qtsshcon.html
termtel/static/qtsshcon_light.html
termtel/static/sshconfrontend.js
termtel/static/xterm-addon-fit.min.js
termtel/static/xterm.min.css
termtel/static/xterm.min.js
termtel/static/css/amber
termtel/static/css/dark.css
termtel/static/css/default-save.css
termtel/static/css/retro_green
termtel/static/css/theme-blue.css
termtel/static/css/theme-crt-amber.css
termtel/static/css/theme-crt-green.css
termtel/static/css/theme-crt-mono.css
termtel/static/css/theme-default-green.css
termtel/static/css/theme-default.css
termtel/static/css/theme-forest-green.css
termtel/static/css/theme-forest-light.css
termtel/static/css/theme-green.css
termtel/static/css/theme-light.css
termtel/static/css/theme-paper-white.css
termtel/static/css/theme-paper.css
termtel/static/css/velociterm.css
termtel/static/css/xterm.css
termtel/static/images/python.png
termtel/static/images/python1.png
termtel/static/images/python2.png
termtel/static/js/custom.js
termtel/static/js/velociterm.js
terminaltelemetry-1.0.0.dist-info/METADATA
terminaltelemetry-1.0.0.dist-info/WHEEL
terminaltelemetry-1.0.0.dist-info/entry_points.txt
terminaltelemetry-1.0.0.dist-info/top_level.txt
terminaltelemetry-1.0.0.dist-info/RECORD
