Metadata-Version: 2.4
Name: TerminalTelemetry
Version: 1.0.0
Summary: A PyQt6 terminal emulator with SSH and telemetry capabilities
Home-page: https://github.com/scottpeterman/terminaltelemetry
Author: Scott Peterman
Author-email: scottpeterman@gmail.com
Project-URL: Source, https://github.com/scottpeterman/terminaltelemetry
Keywords: terminal ssh telemetry network monitoring pyqt6 netmiko textfsm
Classifier: Programming Language :: Python :: 3
Classifier: License :: OSI Approved :: GNU General Public License v3 (GPLv3)
Classifier: Operating System :: OS Independent
Classifier: Environment :: X11 Applications :: Qt
Classifier: Topic :: System :: Networking :: Monitoring
Classifier: Topic :: System :: System Shells
Classifier: Topic :: Terminals :: Terminal Emulators/X Terminals
Requires-Python: >=3.12
License-File: LICENSE
Requires-Dist: backports.tarfile>=1.2.0
Requires-Dist: bcrypt>=4.2.1
Requires-Dist: certifi>=2025.1.31
Requires-Dist: cffi>=1.17.1
Requires-Dist: charset-normalizer>=3.4.1
Requires-Dist: click>=8.1.8
Requires-Dist: colorama>=0.4.6
Requires-Dist: cryptography>=44.0.1
Requires-Dist: diff-match-patch>=20241021
Requires-Dist: docutils>=0.21.2
Requires-Dist: future>=1.0.0
Requires-Dist: id>=1.5.0
Requires-Dist: idna>=3.10
Requires-Dist: importlib_metadata>=8.6.1
Requires-Dist: jaraco.classes>=3.4.0
Requires-Dist: jaraco.context>=6.0.1
Requires-Dist: jaraco.functools>=4.1.0
Requires-Dist: Jinja2>=3.1.5
Requires-Dist: junos-eznc>=2.7.2
Requires-Dist: keyring>=25.6.0
Requires-Dist: logicmonitor-sdk>=3.0.222
Requires-Dist: lxml>=5.3.1
Requires-Dist: markdown-it-py>=3.0.0
Requires-Dist: MarkupSafe>=3.0.2
Requires-Dist: mdurl>=0.1.2
Requires-Dist: more-itertools>=10.6.0
Requires-Dist: napalm>=5.0.0
Requires-Dist: ncclient>=0.6.15
Requires-Dist: netaddr>=1.3.0
Requires-Dist: netmiko>=4.5.0
Requires-Dist: netutils>=1.12.0
Requires-Dist: nh3>=0.2.20
Requires-Dist: ntc_templates>=7.7.0
Requires-Dist: packaging>=24.2
Requires-Dist: paramiko>=3.5.1
Requires-Dist: pkginfo>=1.12.0
Requires-Dist: pycparser>=2.22
Requires-Dist: pyeapi>=1.0.4
Requires-Dist: Pygments>=2.19.1
Requires-Dist: PyNaCl>=1.5.0
Requires-Dist: pynetbox>=7.4.1
Requires-Dist: pyparsing>=3.2.1
Requires-Dist: PyQt6>=6.8.1
Requires-Dist: PyQt6-Charts>=6.8.0
Requires-Dist: PyQt6-Charts-Qt6>=6.8.2
Requires-Dist: PyQt6-Qt6>=6.8.2
Requires-Dist: PyQt6-WebEngine>=6.8.0
Requires-Dist: PyQt6-WebEngine-Qt6>=6.8.2
Requires-Dist: PyQt6_sip>=13.10.0
Requires-Dist: pyserial>=3.5
Requires-Dist: python-dateutil>=2.9.0.post0
Requires-Dist: pywin32-ctypes>=0.2.3
Requires-Dist: PyYAML>=6.0.2
Requires-Dist: qasync>=0.27.1
Requires-Dist: readme_renderer>=44.0
Requires-Dist: requests>=2.32.3
Requires-Dist: requests-toolbelt>=1.0.0
Requires-Dist: rfc3986>=2.0.0
Requires-Dist: rich>=13.9.4
Requires-Dist: ruamel.yaml>=0.18.10
Requires-Dist: ruamel.yaml.clib>=0.2.12
Requires-Dist: scp>=0.15.0
Requires-Dist: setuptools>=75.8.0
Requires-Dist: six>=1.17.0
Requires-Dist: textfsm>=1.1.3
Requires-Dist: transitions>=0.9.2
Requires-Dist: ttp>=0.9.5
Requires-Dist: ttp-templates>=0.3.7
Requires-Dist: twine>=6.1.0
Requires-Dist: typing_extensions>=4.12.2
Requires-Dist: urllib3>=2.3.0
Requires-Dist: yamlordereddictloader>=0.4.2
Requires-Dist: zipp>=3.21.0
Dynamic: author
Dynamic: author-email
Dynamic: classifier
Dynamic: description
Dynamic: description-content-type
Dynamic: home-page
Dynamic: keywords
Dynamic: license-file
Dynamic: project-url
Dynamic: requires-dist
Dynamic: requires-python
Dynamic: summary
